{
  "_format": "hh-sol-cache-2",
  "files": {
    "C:\\Users\\34642\\Desktop\\Escrow-App\\contracts\\Escrow.sol": {
      "lastModificationDate": 1749674664550,
      "contentHash": "9ffb3bd23bce7a01f105124dc0d00701",
      "sourceName": "contracts/Escrow.sol",
      "solcConfig": {
        "version": "0.8.19",
        "settings": {
          "optimizer": {
            "enabled": false,
            "runs": 200
          },
          "outputSelection": {
            "*": {
              "*": [
                "abi",
                "evm.bytecode",
                "evm.deployedBytecode",
                "evm.methodIdentifiers",
                "metadata"
              ],
              "": [
                "ast"
              ]
            }
          }
        }
      },
      "imports": [],
      "versionPragmas": [
        "0.8.19"
      ],
      "artifacts": [
        "Escrow"
      ]
    }
  }
}
